neuroproteomics_analysis_tool/__about__.py
neuroproteomics_analysis_tool/__init__.py
neuroproteomics_analysis_tool/db.py
neuroproteomics_analysis_tool/entry_points.py
neuroproteomics_analysis_tool/npat.py
neuroproteomics_analysis_tool/npat_tui.py
neuroproteomics_analysis_tool/tcss/analyses_analyses_layout.tcss
neuroproteomics_analysis_tool/tcss/analyses_enrichment_analysis_layout.tcss
neuroproteomics_analysis_tool/tcss/analyses_relative_expression_layout.tcss
neuroproteomics_analysis_tool/tcss/analyses_samples_layout.tcss
neuroproteomics_analysis_tool/tcss/database_connection_layout.tcss
neuroproteomics_analysis_tool/tcss/feedback_layout.tcss
neuroproteomics_analysis_tool/tcss/general_layout.tcss
neuroproteomics_analysis_tool/tcss/homepage_layout.tcss
neuroproteomics_analysis_tool-0.0.3.dist-info/METADATA
neuroproteomics_analysis_tool-0.0.3.dist-info/WHEEL
neuroproteomics_analysis_tool-0.0.3.dist-info/entry_points.txt
neuroproteomics_analysis_tool-0.0.3.dist-info/licenses/LICENSE.txt
neuroproteomics_analysis_tool-0.0.3.dist-info/RECORD
